<?xml version="1.0" encoding="UTF-8"?><java-wsdl-mapping version="1.1" xmlns="http://java.sun.com/xml/ns/j2ee" xmlns:xsi="http://www.w3.org/2001/XMLSchema-instance" xsi:schemaLocation="http://java.sun.com/xml/ns/j2ee http://www.ibm.com/webservices/xsd/j2ee_jaxrpc_mapping_1_1.xsd">
    <package-mapping>
        <package-type>com.apria.web.services.mobile.in</package-type>
        <namespaceURI>http://in.mobile.services.web.apria.com</namespaceURI>
    </package-mapping>
    <package-mapping>
        <package-type>com.apria.web.services.mobile.out</package-type>
        <namespaceURI>http://out.mobile.services.web.apria.com</namespaceURI>
    </package-mapping>
    <package-mapping>
        <package-type>com.apria.web.services.mobile</package-type>
        <namespaceURI>http://mobile.services.web.apria.com</namespaceURI>
    </package-mapping>
    <java-xml-type-mapping>
        <java-type>com.apria.web.services.mobile.out.Intake[]</java-type>
        <root-type-qname xmlns:rtq="http://out.mobile.services.web.apria.com">rtq:ArrayOfIntake</root-type-qname>
        <qname-scope>complexType</qname-scope>
        <variable-mapping>
            <java-variable-name>intake</java-variable-name>
            <xml-element-name>Intake</xml-element-name>
        </variable-mapping>
    </java-xml-type-mapping>
    <java-xml-type-mapping>
        <java-type>com.apria.web.services.mobile.out.WorkOrder</java-type>
        <root-type-qname xmlns:rtq="http://out.mobile.services.web.apria.com">rtq:WorkOrder</root-type-qname>
        <qname-scope>complexType</qname-scope>
        <variable-mapping>
            <java-variable-name>associate</java-variable-name>
            <xml-element-name>associate</xml-element-name>
        </variable-mapping>
        <variable-mapping>
            <java-variable-name>completeDate</java-variable-name>
            <xml-element-name>completeDate</xml-element-name>
        </variable-mapping>
        <variable-mapping>
            <java-variable-name>completeTime</java-variable-name>
            <xml-element-name>completeTime</xml-element-name>
        </variable-mapping>
        <variable-mapping>
            <java-variable-name>deliveryDate</java-variable-name>
            <xml-element-name>deliveryDate</xml-element-name>
        </variable-mapping>
        <variable-mapping>
            <java-variable-name>deliveryTime</java-variable-name>
            <xml-element-name>deliveryTime</xml-element-name>
        </variable-mapping>
        <variable-mapping>
            <java-variable-name>EQDate</java-variable-name>
            <xml-element-name>EQDate</xml-element-name>
        </variable-mapping>
        <variable-mapping>
            <java-variable-name>EQTime</java-variable-name>
            <xml-element-name>EQTime</xml-element-name>
        </variable-mapping>
        <variable-mapping>
            <java-variable-name>product1</java-variable-name>
            <xml-element-name>product1</xml-element-name>
        </variable-mapping>
        <variable-mapping>
            <java-variable-name>product2</java-variable-name>
            <xml-element-name>product2</xml-element-name>
        </variable-mapping>
        <variable-mapping>
            <java-variable-name>product3</java-variable-name>
            <xml-element-name>product3</xml-element-name>
        </variable-mapping>
        <variable-mapping>
            <java-variable-name>product4</java-variable-name>
            <xml-element-name>product4</xml-element-name>
        </variable-mapping>
        <variable-mapping>
            <java-variable-name>readyDate</java-variable-name>
            <xml-element-name>readyDate</xml-element-name>
        </variable-mapping>
        <variable-mapping>
            <java-variable-name>readyTime</java-variable-name>
            <xml-element-name>readyTime</xml-element-name>
        </variable-mapping>
        <variable-mapping>
            <java-variable-name>WOCreateDate</java-variable-name>
            <xml-element-name>WOCreateDate</xml-element-name>
        </variable-mapping>
        <variable-mapping>
            <java-variable-name>WOCreateTime</java-variable-name>
            <xml-element-name>WOCreateTime</xml-element-name>
        </variable-mapping>
        <variable-mapping>
            <java-variable-name>deliveryAdressLine1</java-variable-name>
            <xml-element-name>deliveryAdressLine1</xml-element-name>
        </variable-mapping>
        <variable-mapping>
            <java-variable-name>deliveryAdressLine2</java-variable-name>
            <xml-element-name>deliveryAdressLine2</xml-element-name>
        </variable-mapping>
        <variable-mapping>
            <java-variable-name>deliveryCity</java-variable-name>
            <xml-element-name>deliveryCity</xml-element-name>
        </variable-mapping>
        <variable-mapping>
            <java-variable-name>deliveryState</java-variable-name>
            <xml-element-name>deliveryState</xml-element-name>
        </variable-mapping>
        <variable-mapping>
            <java-variable-name>deliveryZipCode</java-variable-name>
            <xml-element-name>deliveryZipCode</xml-element-name>
        </variable-mapping>
        <variable-mapping>
            <java-variable-name>WOStatus</java-variable-name>
            <xml-element-name>WOStatus</xml-element-name>
        </variable-mapping>
        <variable-mapping>
            <java-variable-name>WOStatusDesc</java-variable-name>
            <xml-element-name>WOStatusDesc</xml-element-name>
        </variable-mapping>
        <variable-mapping>
            <java-variable-name>workOrderNO</java-variable-name>
            <xml-element-name>workOrderNO</xml-element-name>
        </variable-mapping>
        <variable-mapping>
            <java-variable-name>intakeNo</java-variable-name>
            <xml-element-name>intakeNo</xml-element-name>
        </variable-mapping>
    </java-xml-type-mapping>
    <java-xml-type-mapping>
        <java-type>com.apria.web.services.mobile.out.WorkOrder[]</java-type>
        <anonymous-type-qname>http://out.mobile.services.web.apria.com:WorkOrder[0,unbounded]</anonymous-type-qname>
        <qname-scope>complexType</qname-scope>
    </java-xml-type-mapping>
    <java-xml-type-mapping>
        <java-type>java.lang.String</java-type>
        <root-type-qname xmlns:rtq="http://www.w3.org/2001/XMLSchema">rtq:string</root-type-qname>
        <qname-scope>simpleType</qname-scope>
    </java-xml-type-mapping>
    <java-xml-type-mapping>
        <java-type>com.apria.web.services.mobile.out.Intake</java-type>
        <root-type-qname xmlns:rtq="http://out.mobile.services.web.apria.com">rtq:Intake</root-type-qname>
        <qname-scope>complexType</qname-scope>
        <variable-mapping>
            <java-variable-name>associate</java-variable-name>
            <xml-element-name>associate</xml-element-name>
        </variable-mapping>
        <variable-mapping>
            <java-variable-name>followpCode</java-variable-name>
            <xml-element-name>followpCode</xml-element-name>
        </variable-mapping>
        <variable-mapping>
            <java-variable-name>IIntakeCreateDate</java-variable-name>
            <xml-element-name>IIntakeCreateDate</xml-element-name>
        </variable-mapping>
        <variable-mapping>
            <java-variable-name>intakeCreateTime</java-variable-name>
            <xml-element-name>intakeCreateTime</xml-element-name>
        </variable-mapping>
        <variable-mapping>
            <java-variable-name>intakeStatus</java-variable-name>
            <xml-element-name>intakeStatus</xml-element-name>
        </variable-mapping>
        <variable-mapping>
            <java-variable-name>intakeStatusDate</java-variable-name>
            <xml-element-name>intakeStatusDate</xml-element-name>
        </variable-mapping>
        <variable-mapping>
            <java-variable-name>intakeStatusTime</java-variable-name>
            <xml-element-name>intakeStatusTime</xml-element-name>
        </variable-mapping>
        <variable-mapping>
            <java-variable-name>patientFirstName</java-variable-name>
            <xml-element-name>patientFirstName</xml-element-name>
        </variable-mapping>
        <variable-mapping>
            <java-variable-name>patientID</java-variable-name>
            <xml-element-name>patientID</xml-element-name>
        </variable-mapping>
        <variable-mapping>
            <java-variable-name>patientLastName</java-variable-name>
            <xml-element-name>patientLastName</xml-element-name>
        </variable-mapping>
        <variable-mapping>
            <java-variable-name>patientMI</java-variable-name>
            <xml-element-name>patientMI</xml-element-name>
        </variable-mapping>
        <variable-mapping>
            <java-variable-name>physicianID</java-variable-name>
            <xml-element-name>physicianID</xml-element-name>
        </variable-mapping>
        <variable-mapping>
            <java-variable-name>physicianName</java-variable-name>
            <xml-element-name>physicianName</xml-element-name>
        </variable-mapping>
        <variable-mapping>
            <java-variable-name>referralID</java-variable-name>
            <xml-element-name>referralID</xml-element-name>
        </variable-mapping>
        <variable-mapping>
            <java-variable-name>referralName</java-variable-name>
            <xml-element-name>referralName</xml-element-name>
        </variable-mapping>
        <variable-mapping>
            <java-variable-name>referralZipCode</java-variable-name>
            <xml-element-name>referralZipCode</xml-element-name>
        </variable-mapping>
        <variable-mapping>
            <java-variable-name>intakeNo</java-variable-name>
            <xml-element-name>intakeNo</xml-element-name>
        </variable-mapping>
        <variable-mapping>
            <java-variable-name>workOrderList</java-variable-name>
            <xml-element-name>workOrderList</xml-element-name>
        </variable-mapping>
    </java-xml-type-mapping>
    <java-xml-type-mapping>
        <java-type>com.apria.web.services.mobile.out.WorkOrder[]</java-type>
        <root-type-qname xmlns:rtq="http://out.mobile.services.web.apria.com">rtq:ArrayOfWorkOrder</root-type-qname>
        <qname-scope>complexType</qname-scope>
        <variable-mapping>
            <java-variable-name>workOrder</java-variable-name>
            <xml-element-name>WorkOrder</xml-element-name>
        </variable-mapping>
    </java-xml-type-mapping>
    <java-xml-type-mapping>
        <java-type>com.apria.web.services.mobile.out.IntakeResult</java-type>
        <root-type-qname xmlns:rtq="http://out.mobile.services.web.apria.com">rtq:IntakeResult</root-type-qname>
        <qname-scope>complexType</qname-scope>
        <variable-mapping>
            <java-variable-name>intakeCount</java-variable-name>
            <xml-element-name>intakeCount</xml-element-name>
        </variable-mapping>
        <variable-mapping>
            <java-variable-name>intakeOverFlow</java-variable-name>
            <xml-element-name>intakeOverFlow</xml-element-name>
        </variable-mapping>
        <variable-mapping>
            <java-variable-name>recCount</java-variable-name>
            <xml-element-name>recCount</xml-element-name>
        </variable-mapping>
        <variable-mapping>
            <java-variable-name>recStatus</java-variable-name>
            <xml-element-name>recStatus</xml-element-name>
        </variable-mapping>
        <variable-mapping>
            <java-variable-name>WOCount</java-variable-name>
            <xml-element-name>WOCount</xml-element-name>
        </variable-mapping>
        <variable-mapping>
            <java-variable-name>intakeList</java-variable-name>
            <xml-element-name>intakeList</xml-element-name>
        </variable-mapping>
    </java-xml-type-mapping>
    <java-xml-type-mapping>
        <java-type>com.apria.web.services.mobile.out.Intake[]</java-type>
        <anonymous-type-qname>http://out.mobile.services.web.apria.com:Intake[0,unbounded]</anonymous-type-qname>
        <qname-scope>complexType</qname-scope>
    </java-xml-type-mapping>
    <java-xml-type-mapping>
        <java-type>com.apria.web.services.mobile.in.SearchRequest</java-type>
        <root-type-qname xmlns:rtq="http://in.mobile.services.web.apria.com">rtq:SearchRequest</root-type-qname>
        <qname-scope>complexType</qname-scope>
        <variable-mapping>
            <java-variable-name>branch</java-variable-name>
            <xml-element-name>branch</xml-element-name>
        </variable-mapping>
        <variable-mapping>
            <java-variable-name>fromDate</java-variable-name>
            <xml-element-name>fromDate</xml-element-name>
        </variable-mapping>
        <variable-mapping>
            <java-variable-name>toDate</java-variable-name>
            <xml-element-name>toDate</xml-element-name>
        </variable-mapping>
        <variable-mapping>
            <java-variable-name>zipCode</java-variable-name>
            <xml-element-name>zipCode</xml-element-name>
        </variable-mapping>
        <variable-mapping>
            <java-variable-name>branchHost</java-variable-name>
            <xml-element-name>branchHost</xml-element-name>
        </variable-mapping>
        <variable-mapping>
            <java-variable-name>intakeStartSeq</java-variable-name>
            <xml-element-name>intakeStartSeq</xml-element-name>
        </variable-mapping>
    </java-xml-type-mapping>
    <java-xml-type-mapping>
        <java-type>com.apria.web.services.mobile.out.WorkOrder[]</java-type>
        <anonymous-type-qname>http://out.mobile.services.web.apria.com:ArrayOfWorkOrder&gt;WorkOrder[0,unbounded]</anonymous-type-qname>
        <qname-scope>complexType</qname-scope>
    </java-xml-type-mapping>
    <java-xml-type-mapping>
        <java-type>com.apria.web.services.mobile.out.Intake[]</java-type>
        <anonymous-type-qname>http://out.mobile.services.web.apria.com:ArrayOfIntake&gt;Intake[0,unbounded]</anonymous-type-qname>
        <qname-scope>complexType</qname-scope>
    </java-xml-type-mapping>
    <service-interface-mapping>
        <service-interface>com.apria.web.services.mobile.MobileAppWSServiceImplService</service-interface>
        <wsdl-service-name xmlns:sim="http://mobile.services.web.apria.com">sim:MobileAppWSServiceImplService</wsdl-service-name>
        <port-mapping>
            <port-name>MobileAppWSServiceImpl</port-name>
            <java-port-name>MobileAppWSServiceImpl</java-port-name>
        </port-mapping>
    </service-interface-mapping>
    <service-endpoint-interface-mapping>
        <service-endpoint-interface>com.apria.web.services.mobile.MobileAppWSServiceImpl</service-endpoint-interface>
        <wsdl-port-type xmlns:seimwpt="http://mobile.services.web.apria.com">seimwpt:MobileAppWSServiceImpl</wsdl-port-type>
        <wsdl-binding xmlns:seimwb="http://mobile.services.web.apria.com">seimwb:MobileAppWSServiceImplSoapBinding</wsdl-binding>
        <service-endpoint-method-mapping>
            <java-method-name>getIntakeWOList</java-method-name>
            <wsdl-operation>getIntakeWOList</wsdl-operation>
            <wrapped-element/>
            <method-param-parts-mapping>
                <param-position>0</param-position>
                <param-type>com.apria.web.services.mobile.in.SearchRequest</param-type>
                <wsdl-message-mapping>
                    <wsdl-message xmlns:mppm="http://mobile.services.web.apria.com">mppm:getIntakeWOListRequest</wsdl-message>
                    <wsdl-message-part-name>request</wsdl-message-part-name>
                    <parameter-mode>IN</parameter-mode>
                </wsdl-message-mapping>
            </method-param-parts-mapping>
            <wsdl-return-value-mapping>
                <method-return-value>com.apria.web.services.mobile.out.IntakeResult</method-return-value>
                <wsdl-message xmlns:wrvm="http://mobile.services.web.apria.com">wrvm:getIntakeWOListResponse</wsdl-message>
                <wsdl-message-part-name>getIntakeWOListReturn</wsdl-message-part-name>
            </wsdl-return-value-mapping>
        </service-endpoint-method-mapping>
    </service-endpoint-interface-mapping>
</java-wsdl-mapping>